pyclrs/__init__.py
pyclrs/color.py
pyclrs-0.0.1.dist-info/LICENSE
pyclrs-0.0.1.dist-info/METADATA
pyclrs-0.0.1.dist-info/WHEEL
pyclrs-0.0.1.dist-info/top_level.txt
pyclrs-0.0.1.dist-info/RECORD
