Metadata-Version: 2.1
Name: pyclrs
Version: 0.0.1
Summary: Print color on Linux or Windows terminals.
Home-page: https://github.com/liuhedong135/pyclrs
Author: Oliven
Author-email: Liuhedong135@163.com
License: UNKNOWN
Platform: UNKNOWN
Classifier: Programming Language :: Python :: 2
Classifier: Programming Language :: Python :: 3
Classifier: License :: OSI Approved :: MIT License
Classifier: Operating System :: OS Independent
